{
  "scan_id": "2026-06-13T09:20:25.047Z",
  "base_url": "https://www.dianping.com/shanghai/ch10/r101937",
  "station": {
    "city": "shanghai",
    "station_name": "静安寺",
    "line_name": "2号线",
    "base_url": "https://www.dianping.com/shanghai/ch10/r101937",
    "notes": null
  },
  "updated_at": "2026-06-13T09:20:53.479Z",
  "count": 45,
  "shops_with_taocan": 7,
  "records": [
    {
      "scan_id": "2026-06-13T09:20:25.047Z",
      "source": {
        "base_url": "https://www.dianping.com/shanghai/ch10/r101937",
        "page_url": "https://www.dianping.com/shanghai/ch10/r101937",
        "page_number": 1,
        "result_index": 1
      },
      "shop": {
        "name": "PAIN CHAUD 百丘(静安久光店)",
        "url": "https://www.dianping.com/shop/G9ndRNFzqERFscf7",
        "shop_id": "G9ndRNFzqERFscf7",
        "image_url": "https://img.meituan.net/content/3e2fb0e1a9515a4ec3e8a1833bdc9d6e66930.jpg%40340w_255h_1e_1c_1l%7Cwatermark%3D0",
        "name_pinyin": "PAIN CHAUD bai qiu ( jing an jiu guang dian )",
        "address": "南京西路1618号久光百货1楼S102室",
        "address_pinyin": "nan jing xi lu 1618 hao jiu guang bai huo 1 lou S102 shi",
        "rating": 4.1,
        "review_count": 10506,
        "avg_price_per_person": 50,
        "area": null,
        "category": "静安寺商圈面包蛋糕",
        "score_breakdown": {
          "口味": 4.1,
          "环境": 4.2,
          "服务": 4.2
        },
        "ranking_badge": "静安寺商圈面包蛋糕销量榜 · 第3名",
        "open_status": "营业中",
        "opening_hours": "07:30-21:30",
        "distance_from_station": {
          "raw_text": "距地铁静安寺站出入口步行150m",
          "transit_text": "静安寺站出入口",
          "walking_distance_meters": 150
        },
        "amenities": [
          "付费停车"
        ],
        "recommended_dishes": [
          "开心果泡芙",
          "冰淇淋",
          "柠檬挞",
          "可颂",
          "迷你红酒无花果",
          "法棍",
          "栗子挞",
          "小玉米面包",
          "杏仁可颂",
          "小杂粮包"
        ],
        "menu_count": 4,
        "review_section_count": null,
        "amap_location": {
          "lng": 121.446332,
          "lat": 31.223814,
          "formatted_address": null,
          "level": null,
          "query": "上海南京西路1618号久光百货1楼S102室",
          "source": "amap_js_browser",
          "geocoded_at": "2026-06-13T11:26:12.496Z"
        }
      },
      "offers": [
        {
          "type": "voucher",
          "title": "90元代金券",
          "price": 86,
          "currency": "CNY",
          "discount": "9.6折",
          "original_price": null,
          "flags": [
            "随时退",
            "过期自动退"
          ],
          "details": {
            "group_size": null,
            "valid_time": null,
            "earliest_usable": null
          },
          "raw_text": "90元代金券 随时退 过期自动退 ¥ 86 9.6折 买券",
          "image_url": null
        },
        {
          "type": "taocan",
          "title": "【人气特惠】法式冰淇淋单人餐（口味4选1）",
          "price": 19.9,
          "currency": "CNY",
          "discount": "6.7折",
          "original_price": 30,
          "flags": [
            "随时退",
            "过期自动退"
          ],
          "details": {
            "group_size": "单人",
            "valid_time": "周一至周日",
            "earliest_usable": null,
            "valid_time_en": "Monday to Sunday"
          },
          "raw_text": "【人气特惠】法式冰淇淋单人餐（口味4选1） 周一至周日 随时退 过期自动退 ¥ 19.9 6.7折 ￥30 抢购",
          "image_url": "https://img.meituan.net/content/e02d5c06dcae2f1ebb8ce5023a93a4ab357932.jpg%40168w_168h_1e_1c_1l%7Cwatermark%3D0",
          "title_en": "Popular special: French ice cream set for one, choose one of four flavors"
        },
        {
          "type": "taocan",
          "title": "【福利】热拿铁双人餐",
          "price": 54,
          "currency": "CNY",
          "discount": "8.5折",
          "original_price": 64,
          "flags": [
            "随时退",
            "过期自动退"
          ],
          "details": {
            "group_size": "双人",
            "valid_time": "周一至周日",
            "earliest_usable": null,
            "valid_time_en": "Monday to Sunday"
          },
          "raw_text": "【福利】热拿铁双人餐 周一至周日 随时退 过期自动退 ¥ 54 8.5折 ￥64 抢购",
          "image_url": "https://img.meituan.net/content/30a4df3f9378158651c698726dd25f2e324177.jpg%40168w_168h_1e_1c_1l%7Cwatermark%3D0",
          "title_en": "Special offer: hot latte set for two"
        }
      ],
      "extraction": {
        "status": "ok",
        "details_hidden": false,
        "captured_at": "2026-06-13T09:20:29.765Z",
        "method": "codex-extension",
        "elapsed_ms": 1449
      }
    },
    {
      "scan_id": "2026-06-13T09:20:25.047Z",
      "source": {
        "base_url": "https://www.dianping.com/shanghai/ch10/r101937",
        "page_url": "https://www.dianping.com/shanghai/ch10/r101937",
        "page_number": 1,
        "result_index": 2
      },
      "shop": {
        "name": "普通食堂·家庭式烤肉(铜仁路店)",
        "url": "https://www.dianping.com/shop/H4UYBW3SeTO0E17U",
        "shop_id": "H4UYBW3SeTO0E17U",
        "image_url": "https://img.meituan.net/content/30b09ae03355c1e7ac01774f7f8dfde550170.jpg%40340w_255h_1e_1c_1l%7Cwatermark%3D0",
        "name_pinyin": "pu tong shi tang · jia ting shi kao rou ( tong ren lu dian )",
        "address": "铜仁路88号L1层L114",
        "address_pinyin": "tong ren lu 88 hao L1 ceng L114",
        "rating": 4.3,
        "review_count": 6331,
        "avg_price_per_person": 165,
        "area": null,
        "category": "南京西路商圈韩式烤肉",
        "score_breakdown": {
          "口味": 4.3,
          "环境": 4.4,
          "服务": 4.5
        },
        "ranking_badge": "南京西路商圈烤肉打卡人气榜 · 第1名",
        "open_status": "营业中",
        "opening_hours": "12:00-15:00, 17:00-次日01:00",
        "distance_from_station": {
          "raw_text": "距地铁7号线静安寺站8口步行280m",
          "transit_text": "7号线静安寺站8口",
          "walking_distance_meters": 280
        },
        "amenities": [],
        "recommended_dishes": [
          "奶奶的辣年糕条",
          "冷三肉",
          "火山芝士鸡蛋糕",
          "黑猪五花肉",
          "厚切吊龙",
          "烤肉小哥哥",
          "芝士玉米",
          "辣炒海灵菇",
          "大酱汤",
          "厚切猪颈肉"
        ],
        "menu_count": 40,
        "review_section_count": null,
        "amap_location": {
          "lng": 121.451315,
          "lat": 31.223418,
          "formatted_address": null,
          "level": null,
          "query": "上海铜仁路88号L1层L114",
          "source": "amap_js_browser",
          "geocoded_at": "2026-06-13T11:26:12.496Z"
        }
      },
      "offers": [],
      "extraction": {
        "status": "ok",
        "details_hidden": false,
        "captured_at": "2026-06-13T09:20:30.595Z",
        "method": "codex-extension",
        "elapsed_ms": 824
      }
    },
    {
      "scan_id": "2026-06-13T09:20:25.047Z",
      "source": {
        "base_url": "https://www.dianping.com/shanghai/ch10/r101937",
        "page_url": "https://www.dianping.com/shanghai/ch10/r101937",
        "page_number": 1,
        "result_index": 3
      },
      "shop": {
        "name": "浩海火燒雲傣家菜(芮欧百货店)",
        "url": "https://www.dianping.com/shop/H90u0jvX1RDjX8dg",
        "shop_id": "H90u0jvX1RDjX8dg",
        "image_url": "http://p0.meituan.net/biztone/8cf27eb07544d8f5beeed34d79adb83b461329.jpg%40340w_255h_1e_1c_1l%7Cwatermark%3D0",
        "name_pinyin": "hao hai huo shao yun dai jia cai ( rui ou bai huo dian )",
        "address": "南京西路1601号芮欧百货4层4A",
        "address_pinyin": "nan jing xi lu 1601 hao rui ou bai huo 4 ceng 4A",
        "rating": 4.6,
        "review_count": 50803,
        "avg_price_per_person": 108,
        "area": null,
        "category": "静安寺商圈云南菜|滇菜",
        "score_breakdown": {
          "口味": 4.6,
          "环境": 4.5,
          "服务": 4.6
        },
        "ranking_badge": "上海云南菜|滇菜热门榜 · 第1名",
        "open_status": "营业中",
        "opening_hours": "10:30-22:00",
        "distance_from_station": {
          "raw_text": "距地铁静安寺站4口步行200m",
          "transit_text": "静安寺站4口",
          "walking_distance_meters": 200
        },
        "amenities": [
          "付费停车",
          "有宝宝椅"
        ],
        "recommended_dishes": [
          "土司铜锅油焖鸡",
          "黑三剁",
          "小锅米线",
          "蒜香鸡脚",
          "牛肉饵丝",
          "蒜香拼盘",
          "凉拌荷包蛋",
          "确实自己酿的浓浆原味米酒",
          "酸笋炒空心菜",
          "玫瑰花生冰粉"
        ],
        "menu_count": 41,
        "review_section_count": null,
        "amap_location": {
          "lng": 121.447323,
          "lat": 31.22327,
          "formatted_address": null,
          "level": null,
          "query": "上海南京西路1601号芮欧百货4层4A",
          "source": "amap_js_browser",
          "geocoded_at": "2026-06-13T11:26:12.496Z"
        }
      },
      "offers": [],
      "extraction": {
        "status": "ok",
        "details_hidden": false,
        "captured_at": "2026-06-13T09:20:31.396Z",
        "method": "codex-extension",
        "elapsed_ms": 795
      }
    },
    {
      "scan_id": "2026-06-13T09:20:25.047Z",
      "source": {
        "base_url": "https://www.dianping.com/shanghai/ch10/r101937",
        "page_url": "https://www.dianping.com/shanghai/ch10/r101937",
        "page_number": 1,
        "result_index": 4
      },
      "shop": {
        "name": "FASCINO Selection(久光百货店)",
        "url": "https://www.dianping.com/shop/Ga32MhZqsDPgepzN",
        "shop_id": "Ga32MhZqsDPgepzN",
        "image_url": "https://img.meituan.net/content/9730f8b771d41c0a7fe168fb233b123e105033.jpg%40340w_255h_1e_1c_1l%7Cwatermark%3D0",
        "name_pinyin": "FASCINO Selection( jiu guang bai huo dian )",
        "address": "南京西路1618号久光百货b1",
        "address_pinyin": "nan jing xi lu 1618 hao jiu guang bai huo b1",
        "rating": 3.8,
        "review_count": 2865,
        "avg_price_per_person": 35,
        "area": null,
        "category": "静安寺商圈面包蛋糕",
        "score_breakdown": {
          "口味": 3.9,
          "环境": 3.9,
          "服务": 3.9
        },
        "ranking_badge": null,
        "open_status": "营业中",
        "opening_hours": "08:30-22:00",
        "distance_from_station": {
          "raw_text": "距地铁静安寺站2口步行20m",
          "transit_text": "静安寺站2口",
          "walking_distance_meters": 20
        },
        "amenities": [
          "付费停车"
        ],
        "recommended_dishes": [
          "乳酪贝果",
          "京都三色贝果",
          "伯爵苹果贝果",
          "芝麻贝果",
          "海盐生乳卷",
          "芋泥奶霜泡芙",
          "芝麻豆乳卷",
          "姜黄金枪鱼贝果",
          "桂花紫薯贝果",
          "开心果布蕾泡芙"
        ],
        "menu_count": 2,
        "review_section_count": null,
        "amap_location": {
          "lng": 121.446268,
          "lat": 31.223906,
          "formatted_address": null,
          "level": null,
          "query": "上海南京西路1618号久光百货b1",
          "source": "amap_js_browser",
          "geocoded_at": "2026-06-13T11:26:12.496Z"
        }
      },
      "offers": [
        {
          "type": "taocan",
          "title": "蜂蜜蛋糕礼盒",
          "price": 70,
          "currency": "CNY",
          "discount": "8.8折",
          "original_price": 80,
          "flags": [
            "随时退",
            "过期自动退"
          ],
          "details": {
            "group_size": null,
            "valid_time": "周一至周日",
            "earliest_usable": null,
            "valid_time_en": "Monday to Sunday"
          },
          "raw_text": "蜂蜜蛋糕礼盒 周一至周日 随时退 过期自动退 ¥ 70 8.8折 ￥80 抢购",
          "image_url": "http://p0.meituan.net/content/6b560bbae712daccc92c211357f13f5e1269699.png%40168w_168h_1e_1c_1l%7Cwatermark%3D0",
          "title_en": "Honey cake gift box"
        },
        {
          "type": "taocan",
          "title": "馥郁伴手礼盒",
          "price": 210,
          "currency": "CNY",
          "discount": "9.7折",
          "original_price": 218,
          "flags": [
            "随时退",
            "过期自动退"
          ],
          "details": {
            "group_size": null,
            "valid_time": "周一至周日",
            "earliest_usable": null,
            "valid_time_en": "Monday to Sunday"
          },
          "raw_text": "馥郁伴手礼盒 周一至周日 随时退 过期自动退 ¥ 210 9.7折 ￥218 抢购",
          "image_url": "https://img.meituan.net/content/96e8550da1fff215273a6445be54f291134728.jpg%40168w_168h_1e_1c_1l%7Cwatermark%3D0",
          "title_en": "Richly flavored gift box"
        }
      ],
      "extraction": {
        "status": "ok",
        "details_hidden": false,
        "captured_at": "2026-06-13T09:20:32.230Z",
        "method": "codex-extension",
        "elapsed_ms": 825
      }
    },
    {
      "scan_id": "2026-06-13T09:20:25.047Z",
      "source": {
        "base_url": "https://www.dianping.com/shanghai/ch10/r101937",
        "page_url": "https://www.dianping.com/shanghai/ch10/r101937",
        "page_number": 1,
        "result_index": 5
      },
      "shop": {
        "name": "Maki House寿司(CP静安店)",
        "url": "https://www.dianping.com/shop/l47cLtydTj99mTJk",
        "shop_id": "l47cLtydTj99mTJk",
        "image_url": "https://p0.meituan.net/biztone/1a04bb37772a80a549dfee38ae74551b190561.jpg%40340w_255h_1e_1c_1l%7Cwatermark%3D0",
        "name_pinyin": "Maki House shou si (CP jing an dian )",
        "address": "愚园路8号CP静安四楼L4-12室",
        "address_pinyin": "yu yuan lu 8 hao CP jing an si lou L4-12 shi",
        "rating": 4.7,
        "review_count": 27294,
        "avg_price_per_person": 136,
        "area": null,
        "category": "静安寺商圈寿司",
        "score_breakdown": {
          "口味": 4.7,
          "环境": 4.6,
          "服务": 4.6
        },
        "ranking_badge": "静安区寿司热门榜 · 第2名",
        "open_status": "营业中",
        "opening_hours": "11:30-14:00, 17:00-21:00",
        "distance_from_station": {
          "raw_text": "距地铁静安寺站3口步行370m",
          "transit_text": "静安寺站3口",
          "walking_distance_meters": 370
        },
        "amenities": [
          "有大桌",
          "免费停车",
          "有宝宝椅"
        ],
        "recommended_dishes": [
          "招牌鹅肝寿司",
          "牛排饭",
          "鳗鱼饭",
          "三文鱼刺身",
          "三文鱼腩",
          "帝王蟹肉凯撒色拉",
          "鲜虾牛油果卷",
          "焦糖布丁",
          "香煎牛舌",
          "甜虾刺"
        ],
        "menu_count": 64,
        "review_section_count": null,
        "amap_location": {
          "lng": 121.447089,
          "lat": 31.225874,
          "formatted_address": null,
          "level": null,
          "query": "上海愚园路8号CP静安四楼L4-12室",
          "source": "amap_js_browser",
          "geocoded_at": "2026-06-13T11:26:12.496Z"
        }
      },
      "offers": [],
      "extraction": {
        "status": "ok",
        "details_hidden": false,
        "captured_at": "2026-06-13T09:20:33.070Z",
        "method": "codex-extension",
        "elapsed_ms": 837
      }
    },
    {
      "scan_id": "2026-06-13T09:20:25.047Z",
      "source": {
        "base_url": "https://www.dianping.com/shanghai/ch10/r101937",
        "page_url": "https://www.dianping.com/shanghai/ch10/r101937",
        "page_number": 1,
        "result_index": 6
      },
      "shop": {
        "name": "O'mills Sourdough Bakery&Bistro(嘉里中心店)",
        "url": "https://www.dianping.com/shop/k1xGqLcipxN8Szch",
        "shop_id": "k1xGqLcipxN8Szch",
        "image_url": "https://p0.meituan.net/biztone/cc6a14e377b3b5f83da6aefa6ca8a595506899.jpg%40340w_255h_1e_1c_1l%7Cwatermark%3D0",
        "name_pinyin": "O'mills Sourdough Bakery&Bistro( jia li zhong xin dian )",
        "address": "距地铁7号线静安寺站6口步行170m",
        "address_pinyin": "ju di tie 7 hao xian jing an si zhan 6 kou bu xing 170m",
        "rating": 4.3,
        "review_count": 9203,
        "avg_price_per_person": 129,
        "area": "静安寺商圈",
        "category": "西餐",
        "score_breakdown": {
          "口味": 4.4,
          "环境": 4.4,
          "服务": 4.4
        },
        "ranking_badge": null,
        "open_status": "营业中",
        "opening_hours": "08:30-22:00",
        "distance_from_station": {
          "raw_text": "距地铁7号线静安寺站6口步行170m",
          "transit_text": "7号线静安寺站6口",
          "walking_distance_meters": 170
        },
        "amenities": [
          "付费停车",
          "有宝宝椅"
        ],
        "recommended_dishes": [
          "超级牛肉帕尼尼",
          "谷饲肉眼牛排沙拉",
          "水牛芝士玛格丽特",
          "无花果沙拉",
          "酸面包",
          "牛油果沙拉",
          "有机温泉蛋牛油果乡村吐司",
          "黑松露野酵母披萨",
          "三文鱼意面",
          "东坡牛肋排拼盘"
        ],
        "menu_count": 36,
        "review_section_count": null,
        "amap_location": {
          "lng": 121.44532,
          "lat": 31.223505,
          "formatted_address": null,
          "level": null,
          "query": "上海静安寺商圈距地铁7号线静安寺站6口步行170m",
          "source": "amap_js_browser",
          "geocoded_at": "2026-06-13T11:26:12.496Z"
        }
      },
      "offers": [],
      "extraction": {
        "status": "ok",
        "details_hidden": false,
        "captured_at": "2026-06-13T09:20:33.927Z",
        "method": "codex-extension",
        "elapsed_ms": 853
      }
    },
    {
      "scan_id": "2026-06-13T09:20:25.047Z",
      "source": {
        "base_url": "https://www.dianping.com/shanghai/ch10/r101937",
        "page_url": "https://www.dianping.com/shanghai/ch10/r101937",
        "page_number": 1,
        "result_index": 7
      },
      "shop": {
        "name": "春风松月楼(久光百货店)",
        "url": "https://www.dianping.com/shop/E1GOy9LEdOq3cTFC",
        "shop_id": "E1GOy9LEdOq3cTFC",
        "image_url": "https://img.meituan.net/content/def8c00d246c096b409490aa07f2ac5783039.jpg%40340w_255h_1e_1c_1l%7Cwatermark%3D0",
        "name_pinyin": "chun feng song yue lou ( jiu guang bai huo dian )",
        "address": "距地铁2号线静安寺地铁站出入口20m",
        "address_pinyin": "ju di tie 2 hao xian jing an si di tie zhan chu ru kou 20m",
        "rating": 3.8,
        "review_count": 5788,
        "avg_price_per_person": 32,
        "area": null,
        "category": "静安寺商圈包子",
        "score_breakdown": {
          "口味": 3.9,
          "环境": 3.9,
          "服务": 3.9
        },
        "ranking_badge": "静安寺商圈包子热门榜 · 第3名",
        "open_status": "营业中",
        "opening_hours": "09:00-22:00",
        "distance_from_station": null,
        "amenities": [
          "付费停车",
          "有宝宝椅"
        ],
        "recommended_dishes": [
          "招牌净素菜包",
          "松月楼素蟹粉拌面",
          "金牌香菇面筋面",
          "净素香菇馅烧麦",
          "原创素蟹粉包子",
          "传统香素鸭",
          "本帮传统辣酱面",
          "净素甜糯豆沙包",
          "一口香素馄饨",
          "本帮豆腐皮包子"
        ],
        "menu_count": 68,
        "review_section_count": null,
        "amap_location": {
          "lng": 121.446533,
          "lat": 31.223231,
          "formatted_address": null,
          "level": null,
          "query": "上海距地铁2号线静安寺地铁站出入口20m",
          "source": "amap_js_browser",
          "geocoded_at": "2026-06-13T11:26:12.496Z"
        }
      },
      "offers": [],
      "extraction": {
        "status": "ok",
        "details_hidden": false,
        "captured_at": "2026-06-13T09:20:34.755Z",
        "method": "codex-extension",
        "elapsed_ms": 822
      }
    },
    {
      "scan_id": "2026-06-13T09:20:25.047Z",
      "source": {
        "base_url": "https://www.dianping.com/shanghai/ch10/r101937",
        "page_url": "https://www.dianping.com/shanghai/ch10/r101937",
        "page_number": 1,
        "result_index": 8
      },
      "shop": {
        "name": "沪西老弄堂面馆(静安寺店)",
        "url": "https://www.dianping.com/shop/l5uh6bCVt12QboDC",
        "shop_id": "l5uh6bCVt12QboDC",
        "image_url": "https://img.meituan.net/msmerchant/1583a268a16ea983d48346595a7e159e132091.jpg%40340w_255h_1e_1c_1l%7Cwatermark%3D0",
        "name_pinyin": "hu xi lao long tang mian guan ( jing an si dian )",
        "address": "北京西路1738号",
        "address_pinyin": "bei jing xi lu 1738 hao",
        "rating": 4.3,
        "review_count": 18480,
        "avg_price_per_person": 41,
        "area": "静安寺商圈",
        "category": "面馆",
        "score_breakdown": {
          "口味": 4.3,
          "环境": 4.2,
          "服务": 4.4
        },
        "ranking_badge": "静安区面馆好评榜 · 第1名",
        "open_status": "营业中",
        "opening_hours": "10:00-15:00, 16:00-20:30",
        "distance_from_station": {
          "raw_text": "距地铁静安寺站1口步行330m",
          "transit_text": "静安寺站1口",
          "walking_distance_meters": 330
        },
        "amenities": [
          "付费停车",
          "有宝宝椅"
        ],
        "recommended_dishes": [
          "蛤蜊猪肝拌面",
          "炸猪排",
          "辣肉拌面",
          "大肠拌面",
          "腰花拌面",
          "素鸡",
          "荷包蛋",
          "葱油拌面",
          "虎皮蛋",
          "茄盒"
        ],
        "menu_count": null,
        "review_section_count": null,
        "amap_location": {
          "lng": 121.44336,
          "lat": 31.22491,
          "formatted_address": null,
          "level": null,
          "query": "上海静安寺商圈北京西路1738号",
          "source": "amap_js_browser",
          "geocoded_at": "2026-06-13T11:26:12.496Z"
        }
      },
      "offers": [],
      "extraction": {
        "status": "ok",
        "details_hidden": false,
        "captured_at": "2026-06-13T09:20:35.588Z",
        "method": "codex-extension",
        "elapsed_ms": 827
      }
    },
    {
      "scan_id": "2026-06-13T09:20:25.047Z",
      "source": {
        "base_url": "https://www.dianping.com/shanghai/ch10/r101937",
        "page_url": "https://www.dianping.com/shanghai/ch10/r101937",
        "page_number": 1,
        "result_index": 9
      },
      "shop": {
        "name": "鸿姐老火锅(静安店)",
        "url": "https://www.dianping.com/shop/F4nE08K09Ptc47y4",
        "shop_id": "F4nE08K09Ptc47y4",
        "image_url": "https://img.meituan.net/content/e4d914eca5dfe5fcf6d2d84afe260de5207730.jpg%40340w_255h_1e_1c_1l%7Cwatermark%3D0",
        "name_pinyin": "hong jie lao huo guo ( jing an dian )",
        "address": "愚园东路20号东海广场4号楼1层,可承接各类团建聚餐",
        "address_pinyin": "yu yuan dong lu 20 hao dong hai guang chang 4 hao lou 1 ceng , ke cheng jie ge lei tuan jian ju can",
        "rating": 4.5,
        "review_count": 32102,
        "avg_price_per_person": 120,
        "area": "静安寺商圈重庆",
        "category": "火锅",
        "score_breakdown": {
          "口味": 4.5,
          "环境": 4.4,
          "服务": 4.5
        },
        "ranking_badge": "静安区重庆火锅好评榜 · 第2名",
        "open_status": "营业中",
        "opening_hours": "11:00-次日04:00",
        "distance_from_station": {
          "raw_text": "距地铁7号线静安寺站6口步行430m",
          "transit_text": "7号线静安寺站6口",
          "walking_distance_meters": 430
        },
        "amenities": [
          "有大桌",
          "付费停车"
        ],
        "recommended_dishes": [
          "嫩牛肉",
          "鲜毛肚",
          "鲜鸭血",
          "山城小酥肉",
          "小酥肉",
          "手工蛋煎糍粑",
          "醪糟冰汤圆",
          "马蹄鱼籽虾滑",
          "空运血毛肚",
          "鲜鹅肠"
        ],
        "menu_count": 4,
        "review_section_count": null,
        "amap_location": {
          "lng": 121.449134,
          "lat": 31.226472,
          "formatted_address": null,
          "level": null,
          "query": "上海静安寺商圈重庆愚园东路20号东海广场4号楼1层,可承接各类团建聚餐",
          "source": "amap_js_browser",
          "geocoded_at": "2026-06-13T11:26:12.496Z"
        }
      },
      "offers": [
        {
          "type": "voucher",
          "title": "【结账必用】100元代金券",
          "price": 98,
          "currency": "CNY",
          "discount": "9.8折",
          "original_price": null,
          "flags": [
            "随时退",
            "过期自动退"
          ],
          "details": {
            "group_size": null,
            "valid_time": null,
            "earliest_usable": null
          },
          "raw_text": "【结账必用】100元代金券 随时退 过期自动退 ¥ 98 9.8折 买券",
          "image_url": null
        },
        {
          "type": "taocan",
          "title": "洛神山楂水",
          "price": 1.88,
          "currency": "CNY",
          "discount": "1.6折",
          "original_price": 12,
          "flags": [
            "随时退",
            "过期自动退"
          ],
          "details": {
            "group_size": null,
            "valid_time": "周一至周日",
            "earliest_usable": null,
            "valid_time_en": "Monday to Sunday"
          },
          "raw_text": "洛神山楂水 周一至周日 随时退 过期自动退 ¥ 1.88 1.6折 ￥12 抢购",
          "image_url": "https://img.meituan.net/content/7dc40f600663ad0da1716b2e278ad24f169179.jpg%40168w_168h_1e_1c_1l%7Cwatermark%3D0",
          "title_en": "Roselle hawthorn drink"
        },
        {
          "type": "taocan",
          "title": "夏日俱乐部·招牌热辣双人餐",
          "price": 198,
          "currency": "CNY",
          "discount": "8.5折",
          "original_price": 235,
          "flags": [
            "随时退",
            "过期自动退"
          ],
          "details": {
            "group_size": "双人",
            "valid_time": "周一至周日",
            "earliest_usable": null,
            "valid_time_en": "Monday to Sunday"
          },
          "raw_text": "夏日俱乐部·招牌热辣双人餐 周一至周日 随时退 过期自动退 ¥ 198 8.5折 ￥235 抢购",
          "image_url": "https://img.meituan.net/168.168/content/77b43e37d347c4aac9407b6379941f5d3037636.gif.webp",
          "title_en": "Summer club signature spicy set for two"
        }
      ],
      "extraction": {
        "status": "ok",
        "details_hidden": false,
        "captured_at": "2026-06-13T09:20:36.391Z",
        "method": "codex-extension",
        "elapsed_ms": 790
      }
    },
    {
      "scan_id": "2026-06-13T09:20:25.047Z",
      "source": {
        "base_url": "https://www.dianping.com/shanghai/ch10/r101937",
        "page_url": "https://www.dianping.com/shanghai/ch10/r101937",
        "page_number": 1,
        "result_index": 10
      },
      "shop": {
        "name": "王家沙点心状元(静安寺店)",
        "url": "https://www.dianping.com/shop/HasyBZXCJOHNiOKy",
        "shop_id": "HasyBZXCJOHNiOKy",
        "image_url": "https://img.meituan.net/content/e2884758c2d2a7319c00674cda978868130569.jpg%40340w_255h_1e_1c_1l%7Cwatermark%3D0",
        "name_pinyin": "wang jia sha dian xin zhuang yuan ( jing an si dian )",
        "address": "北京西路1535号",
        "address_pinyin": "bei jing xi lu 1535 hao",
        "rating": 3.9,
        "review_count": 3412,
        "avg_price_per_person": 37,
        "area": "静安寺商圈",
        "category": "小吃",
        "score_breakdown": {
          "口味": 3.9,
          "环境": 3.9,
          "服务": 3.9
        },
        "ranking_badge": "静安区小吃打卡人气榜 · 第2名",
        "open_status": "营业中",
        "opening_hours": "07:00-24:00",
        "distance_from_station": {
          "raw_text": "距地铁静安寺站3口步行560m",
          "transit_text": "静安寺站3口",
          "walking_distance_meters": 560
        },
        "amenities": [
          "免费停车",
          "有宝宝椅"
        ],
        "recommended_dishes": [
          "马兰头青团",
          "蟹粉小笼",
          "辣肉冷面",
          "艾叶细沙青团",
          "苔条净素月饼",
          "虾肉小馄饨",
          "榨菜鲜肉月饼",
          "点心",
          "艾叶咸蛋黄肉松青团",
          "铁板牛肉炒面"
        ],
        "menu_count": 6,
        "review_section_count": null,
        "amap_location": {
          "lng": 121.44651,
          "lat": 31.226763,
          "formatted_address": null,
          "level": null,
          "query": "上海静安寺商圈北京西路1535号",
          "source": "amap_js_browser",
          "geocoded_at": "2026-06-13T11:26:12.496Z"
        }
      },
      "offers": [
        {
          "type": "taocan",
          "title": "端午飘香礼盒",
          "price": 100,
          "currency": "CNY",
          "discount": "9.2折",
          "original_price": 109,
          "flags": [
            "随时退",
            "过期自动退"
          ],
          "details": {
            "group_size": null,
            "valid_time": "周一至周日",
            "earliest_usable": null,
            "valid_time_en": "Monday to Sunday"
          },
          "raw_text": "端午飘香礼盒 周一至周日 随时退 过期自动退 ¥ 100 9.2折 ￥109 抢购",
          "image_url": "http://p0.meituan.net/deal/de6261be1bba5912b489368ffbb823d61330962.jpg%40168w_168h_1e_1c_1l%7Cwatermark%3D0",
          "title_en": "Dragon Boat Festival fragrant gift box"
        },
        {
          "type": "taocan",
          "title": "粽横四海礼盒",
          "price": 150,
          "currency": "CNY",
          "discount": "9.4折",
          "original_price": 160,
          "flags": [
            "随时退",
            "过期自动退"
          ],
          "details": {
            "group_size": null,
            "valid_time": "周一至周日",
            "earliest_usable": null,
            "valid_time_en": "Monday to Sunday"
          },
          "raw_text": "粽横四海礼盒 周一至周日 随时退 过期自动退 ¥ 150 9.4折 ￥160 抢购",
          "image_url": "http://p0.meituan.net/deal/cabbd622d4498ed145c1ddf67f75e348734400.jpg%40168w_168h_1e_1c_1l%7Cwatermark%3D0",
          "title_en": "Zongzi gift box"
        }
      ],
      "extraction": {
        "status": "ok",
        "details_hidden": false,
        "captured_at": "2026-06-13T09:20:37.250Z",
        "method": "codex-extension",
        "elapsed_ms": 856
      }
    },
    {
      "scan_id": "2026-06-13T09:20:25.047Z",
      "source": {
        "base_url": "https://www.dianping.com/shanghai/ch10/r101937",
        "page_url": "https://www.dianping.com/shanghai/ch10/r101937",
        "page_number": 1,
        "result_index": 11
      },
      "shop": {
        "name": "龍记香港茶餐厅(久光百货店)",
        "url": "https://www.dianping.com/shop/GagcZVZpLDQAiXyY",
        "shop_id": "GagcZVZpLDQAiXyY",
        "image_url": "http://p1.meituan.net/biztone/1d04f3106a8bb0ee0a2889b66675286f63703.jpg%40340w_255h_1e_1c_1l%7Cwatermark%3D0",
        "name_pinyin": "long ji xiang gang cha can ting ( jiu guang bai huo dian )",
        "address": "南京西路1618号久光百货B1楼",
        "address_pinyin": "nan jing xi lu 1618 hao jiu guang bai huo B1 lou",
        "rating": 3.5,
        "review_count": 17784,
        "avg_price_per_person": 83,
        "area": "静安寺商圈",
        "category": "茶餐厅",
        "score_breakdown": {
          "口味": 3.7,
          "环境": 3.7,
          "服务": 3.5
        },
        "ranking_badge": "静安区茶餐厅热门榜 · 第9名",
        "open_status": "营业中",
        "opening_hours": "10:00-22:00",
        "distance_from_station": {
          "raw_text": "距地铁静安寺站出入口步行110m",
          "transit_text": "静安寺站出入口",
          "walking_distance_meters": 110
        },
        "amenities": [
          "付费停车"
        ],
        "recommended_dishes": [
          "金牌烧鹅",
          "玫瑰豉油鸡",
          "金牌奶茶",
          "驰名烧鸭",
          "龙记四宝饭",
          "港式菠萝油",
          "鲜虾净云吞",
          "干炒叉烧乌冬",
          "烧味拼盘",
          "招牌艇仔粥"
        ],
        "menu_count": 65,
        "review_section_count": null,
        "amap_location": {
          "lng": 121.446037,
          "lat": 31.223699,
          "formatted_address": null,
          "level": null,
          "query": "上海静安寺商圈南京西路1618号久光百货B1楼",
          "source": "amap_js_browser",
          "geocoded_at": "2026-06-13T11:26:12.496Z"
        }
      },
      "offers": [],
      "extraction": {
        "status": "ok",
        "details_hidden": false,
        "captured_at": "2026-06-13T09:20:38.139Z",
        "method": "codex-extension",
        "elapsed_ms": 882
      }
    },
    {
      "scan_id": "2026-06-13T09:20:25.047Z",
      "source": {
        "base_url": "https://www.dianping.com/shanghai/ch10/r101937",
        "page_url": "https://www.dianping.com/shanghai/ch10/r101937",
        "page_number": 1,
        "result_index": 12
      },
      "shop": {
        "name": "Peet's 皮爷咖啡(愚园路店)",
        "url": "https://www.dianping.com/shop/k5wxMmYu8uehIBwX",
        "shop_id": "k5wxMmYu8uehIBwX",
        "image_url": "https://img.meituan.net/content/efeb5e24eedd3322856b00e0c52b6477168411.jpg%40340w_255h_1e_1c_1l%7Cwatermark%3D0",
        "name_pinyin": "Peet's pi ye ka fei ( yu yuan lu dian )",
        "address": "《品·108美食广场》愚园路108号1层（近愚园路与胶州路交叉口）",
        "address_pinyin": "《 pin ·108 mei shi guang chang 》 yu yuan lu 108 hao 1 ceng （ jin yu yuan lu yu jiao zhou lu jiao cha kou ）",
        "rating": 4.3,
        "review_count": 5105,
        "avg_price_per_person": 42,
        "area": "静安寺商圈",
        "category": "咖啡",
        "score_breakdown": {
          "口味": 4.3,
          "环境": 4.4,
          "服务": 4.3
        },
        "ranking_badge": "静安寺商圈咖啡销量榜 · 第2名",
        "open_status": "营业中",
        "opening_hours": "07:30-22:00",
        "distance_from_station": {
          "raw_text": "距地铁静安寺站出入口步行230m",
          "transit_text": "静安寺站出入口",
          "walking_distance_meters": 230
        },
        "amenities": [
          "付费停车"
        ],
        "recommended_dishes": [
          "拿铁咖啡",
          "澳洲小白",
          "经典栗子蛋糕",
          "原味千层蛋糕",
          "芝士分子拿铁",
          "桂花酒酿拿铁",
          "摘星奶砖拿铁",
          "熔岩澳白",
          "抹茶拿铁",
          "摘星拿铁"
        ],
        "menu_count": null,
        "review_section_count": null,
        "amap_location": {
          "lng": 121.440973,
          "lat": 31.231056,
          "formatted_address": null,
          "level": null,
          "query": "上海静安寺商圈《品·108美食广场》愚园路108号1层（近愚园路与胶州路交叉口）",
          "source": "amap_js_browser",
          "geocoded_at": "2026-06-13T11:26:12.496Z"
        }
      },
      "offers": [
        {
          "type": "taocan",
          "title": "【招牌必喝】经典咖啡双杯",
          "price": 61,
          "currency": "CNY",
          "discount": "8折",
          "original_price": 77,
          "flags": [
            "随时退",
            "过期自动退"
          ],
          "details": {
            "group_size": null,
            "valid_time": "周一至周日",
            "earliest_usable": null,
            "valid_time_en": "Monday to Sunday"
          },
          "raw_text": "【招牌必喝】经典咖啡双杯 周一至周日 随时退 过期自动退 ¥ 61 8折 ￥77",
          "image_url": "https://img.meituan.net/content/c2e87323e87ef7ee9a7cf932039f7f93174899.jpg%40168w_168h_1e_1c_1l%7Cwatermark%3D0",
          "title_en": "Signature must-try: two classic coffees"
        },
        {
          "type": "taocan",
          "title": "【新人专享】第一杯招牌咖啡",
          "price": 24.8,
          "currency": "CNY",
          "discount": "6.4折",
          "original_price": 39,
          "flags": [
            "随时退",
            "过期自动退"
          ],
          "details": {
            "group_size": null,
            "valid_time": "周一至周日",
            "earliest_usable": null,
            "valid_time_en": "Monday to Sunday"
          },
          "raw_text": "【新人专享】第一杯招牌咖啡 周一至周日 随时退 过期自动退 ¥ 24.8 6.4折 ￥39",
          "image_url": "https://img.meituan.net/content/3ed8ba83563011baf3d24893f726ade5245417.jpg%40168w_168h_1e_1c_1l%7Cwatermark%3D0",
          "title_en": "New customer special: first signature coffee"
        }
      ],
      "extraction": {
        "status": "ok",
        "details_hidden": false,
        "captured_at": "2026-06-13T09:20:39.068Z",
        "method": "codex-extension",
        "elapsed_ms": 924
      }
    },
    {
      "scan_id": "2026-06-13T09:20:25.047Z",
      "source": {
        "base_url": "https://www.dianping.com/shanghai/ch10/r101937",
        "page_url": "https://www.dianping.com/shanghai/ch10/r101937",
        "page_number": 1,
        "result_index": 13
      },
      "shop": {
        "name": "M Stand(久光百货店)",
        "url": "https://www.dianping.com/shop/k4V5tTpYzPipxXA0",
        "shop_id": "k4V5tTpYzPipxXA0",
        "image_url": "https://img.meituan.net/content/072212ac4deff042db533d83aa2a0a9e46837.jpg%40340w_255h_1e_1c_1l%7Cwatermark%3D0",
        "name_pinyin": "M Stand( jiu guang bai huo dian )",
        "address": "南京西路1618号久光百货2楼（正门旁露天平台）",
        "address_pinyin": "nan jing xi lu 1618 hao jiu guang bai huo 2 lou （ zheng men pang lu tian ping tai ）",
        "rating": 4,
        "review_count": 3596,
        "avg_price_per_person": 37,
        "area": "静安寺商圈",
        "category": "咖啡",
        "score_breakdown": {
          "口味": 4,
          "环境": 4.1,
          "服务": 4
        },
        "ranking_badge": "静安寺商圈咖啡销量榜 · 第4名",
        "open_status": "营业中",
        "opening_hours": "07:00-22:30",
        "distance_from_station": {
          "raw_text": "距地铁静安寺站2口步行20m",
          "transit_text": "静安寺站2口",
          "walking_distance_meters": 20
        },
        "amenities": [
          "付费停车"
        ],
        "recommended_dishes": [
          "燕麦曲奇拿铁",
          "水泥蛋糕",
          "紫拼配澳白",
          "限季特调饮品",
          "招牌水泥芝士蛋糕",
          "西柚冰咖",
          "鲜椰冰咖",
          "冷萃咖啡",
          "海盐芝士黑咖",
          "咸蛋黄千层"
        ],
        "menu_count": 38,
        "review_section_count": null,
        "amap_location": {
          "lng": 121.446155,
          "lat": 31.223978,
          "formatted_address": null,
          "level": null,
          "query": "上海静安寺商圈南京西路1618号久光百货2楼（正门旁露天平台）",
          "source": "amap_js_browser",
          "geocoded_at": "2026-06-13T11:26:12.496Z"
        }
      },
      "offers": [
        {
          "type": "taocan",
          "title": "【第一次喝】招牌特调咖啡（标杯）18选1",
          "price": 27.5,
          "currency": "CNY",
          "discount": "7.3折",
          "original_price": 38,
          "flags": [
            "随时退",
            "过期自动退"
          ],
          "details": {
            "group_size": null,
            "valid_time": "周一至周日",
            "earliest_usable": null,
            "valid_time_en": "Monday to Sunday"
          },
          "raw_text": "【第一次喝】招牌特调咖啡（标杯）18选1 周一至周日 随时退 过期自动退 ¥ 27.5 7.3折 ￥38",
          "image_url": "https://img.meituan.net/content/3d7443088b86e1d11360de0911fc44b1751312.png%40168w_168h_1e_1c_1l%7Cwatermark%3D0",
          "title_en": "First-timer special: signature coffee, standard cup, choose one of 18"
        },
        {
          "type": "taocan",
          "title": "【热销明星款】奶咖单杯",
          "price": 26.6,
          "currency": "CNY",
          "discount": "7折",
          "original_price": 38,
          "flags": [
            "随时退",
            "过期自动退"
          ],
          "details": {
            "group_size": null,
            "valid_time": "周一至周日",
            "earliest_usable": null,
            "valid_time_en": "Monday to Sunday"
          },
          "raw_text": "【热销明星款】奶咖单杯 周一至周日 随时退 过期自动退 ¥ 26.6 7折 ￥38",
          "image_url": "https://img.meituan.net/content/64dc53d5fbbaf3cfb366f9007b0c8fc11462682.png%40168w_168h_1e_1c_1l%7Cwatermark%3D0",
          "title_en": "Best-selling milk coffee, single cup"
        }
      ],
      "extraction": {
        "status": "ok",
        "details_hidden": false,
        "captured_at": "2026-06-13T09:20:39.981Z",
        "method": "codex-extension",
        "elapsed_ms": 909
      }
    },
    {
      "scan_id": "2026-06-13T09:20:25.047Z",
      "source": {
        "base_url": "https://www.dianping.com/shanghai/ch10/r101937",
        "page_url": "https://www.dianping.com/shanghai/ch10/r101937",
        "page_number": 1,
        "result_index": 14
      },
      "shop": {
        "name": "MEL BOURNE Brunch&Bistro猫尔本(静安店)",
        "url": "https://www.dianping.com/shop/k2VW84LQiYC7XMRC",
        "shop_id": "k2VW84LQiYC7XMRC",
        "image_url": "http://p0.meituan.net/biztone/6dfda9e8dcbe5a3035cf2b896f70b13e819650.jpg%40340w_255h_1e_1c_1l%7Cwatermark%3D0",
        "name_pinyin": "MEL BOURNE Brunch&Bistro mao er ben ( jing an dian )",
        "address": "富民路83-3号（醉美梧桐区沿街阳光露台餐厅、停车可导航巨富大厦）",
        "address_pinyin": "fu min lu 83-3 hao （ zui mei wu tong qu yan jie yang guang lu tai can ting 、 ting che ke dao hang ju fu da sha ）",
        "rating": 4.4,
        "review_count": 17459,
        "avg_price_per_person": 139,
        "area": "静安寺商圈",
        "category": "西餐",
        "score_breakdown": {
          "口味": 4.4,
          "环境": 4.6,
          "服务": 4.5
        },
        "ranking_badge": "静安寺商圈西餐打卡人气榜 · 第4名",
        "open_status": "营业中",
        "opening_hours": "10:00-22:00",
        "distance_from_station": null,
        "amenities": [
          "付费停车",
          "有宝宝椅"
        ],
        "recommended_dishes": [
          "墨村炸蛋",
          "香煎虎虾牛油果沙拉",
          "招牌Lu肉汉堡",
          "榛子朗姆酒蛋糕",
          "大堡礁海鲜饭",
          "炭烤鹿肉排",
          "木炭烤巴斯克蛋糕",
          "烟熏三文鱼温泉蛋吐司",
          "鹿肉薄片配吞拿鱼酱",
          "鹿肉塔塔"
        ],
        "menu_count": 8,
        "review_section_count": null,
        "amap_location": {
          "lng": 121.450698,
          "lat": 31.220488,
          "formatted_address": null,
          "level": null,
          "query": "上海静安寺商圈富民路83-3号（醉美梧桐区沿街阳光露台餐厅、停车可导航巨富大厦）",
          "source": "amap_js_browser",
          "geocoded_at": "2026-06-13T11:26:12.496Z"
        }
      },
      "offers": [
        {
          "type": "voucher",
          "title": "100元代金券",
          "price": 98,
          "currency": "CNY",
          "discount": "9.8折",
          "original_price": null,
          "flags": [
            "随时退",
            "过期自动退"
          ],
          "details": {
            "group_size": null,
            "valid_time": null,
            "earliest_usable": null
          },
          "raw_text": "100元代金券 随时退 过期自动退 ¥ 98 9.8折 买券",
          "image_url": null
        },
        {
          "type": "taocan",
          "title": "【营养健康】工作日单人午市套餐",
          "price": 89,
          "currency": "CNY",
          "discount": "4.8折",
          "original_price": 186,
          "flags": [
            "随时退",
            "过期自动退"
          ],
          "details": {
            "group_size": "单人",
            "valid_time": null,
            "earliest_usable": "最早06.15可用",
            "earliest_usable_en": "Available from 06/15"
          },
          "raw_text": "【营养健康】工作日单人午市套餐 最早06.15可用 随时退 过期自动退 ¥ 89 4.8折 ￥186 抢购",
          "image_url": "http://img.meituan.net/content/be0dd407882c80b0bec414b3a85803a2300676.jpg%40168w_168h_1e_1c_1l%7Cwatermark%3D0",
          "title_en": "Healthy weekday lunch set for one"
        },
        {
          "type": "taocan",
          "title": "【招牌主推】情侣约会豪华套餐",
          "price": 481,
          "currency": "CNY",
          "discount": "6.3折",
          "original_price": 766,
          "flags": [
            "随时退",
            "过期自动退"
          ],
          "details": {
            "group_size": null,
            "valid_time": "周一至周日",
            "earliest_usable": null,
            "valid_time_en": "Monday to Sunday"
          },
          "raw_text": "【招牌主推】情侣约会豪华套餐 周一至周日 随时退 过期自动退 ¥ 481 6.3折 ￥766 抢购",
          "image_url": "http://p0.meituan.net/deal/3782615ec9d45d6f9a12b7d2b5479dae319491.jpg%40168w_168h_1e_1c_1l%7Cwatermark%3D0",
          "title_en": "Signature recommended deluxe date set for two"
        }
      ],
      "extraction": {
        "status": "ok",
        "details_hidden": false,
        "captured_at": "2026-06-13T09:20:40.927Z",
        "method": "codex-extension",
        "elapsed_ms": 928
      }
    },
    {
      "scan_id": "2026-06-13T09:20:25.047Z",
      "source": {
        "base_url": "https://www.dianping.com/shanghai/ch10/r101937",
        "page_url": "https://www.dianping.com/shanghai/ch10/r101937",
        "page_number": 1,
        "result_index": 15
      },
      "shop": {
        "name": "山崎面包(静安久光店)",
        "url": "https://www.dianping.com/shop/k5g3v7PLmFuLzSsX",
        "shop_id": "k5g3v7PLmFuLzSsX",
        "image_url": "https://img.meituan.net/content/ce98b3543a94864ba25838477939293e126416.jpg%40340w_255h_1e_1c_1l%7Cwatermark%3D0",
        "name_pinyin": "shan qi mian bao ( jing an jiu guang dian )",
        "address": "静安寺街道南京西路1618号久光百货B1FDB17-19(近静安寺)",
        "address_pinyin": "jing an si jie dao nan jing xi lu 1618 hao jiu guang bai huo B1FDB17-19( jin jing an si )",
        "rating": 3.9,
        "review_count": 9319,
        "avg_price_per_person": 32,
        "area": null,
        "category": "静安寺商圈面包蛋糕",
        "score_breakdown": {
          "口味": 3.9,
          "环境": 3.9,
          "服务": 3.9
        },
        "ranking_badge": "上海吐司菜品榜第7名",
        "open_status": "营业中",
        "opening_hours": "09:00-22:00",
        "distance_from_station": {
          "raw_text": "距地铁静安寺站出入口步行10m",
          "transit_text": "静安寺站出入口",
          "walking_distance_meters": 10
        },
        "amenities": [
          "付费停车"
        ],
        "recommended_dishes": [
          "山崎皇后吐司",
          "蜜红豆吐司",
          "金枪鱼三明治",
          "海盐法国",
          "奶酪香蒜包",
          "海盐咖啡",
          "巧克力松软甜甜圈",
          "巴黎香法式长棍",
          "蛋挞",
          "吉士麻薯"
        ],
        "menu_count": 3,
        "review_section_count": null,
        "amap_location": {
          "lng": 121.446198,
          "lat": 31.223687,
          "formatted_address": null,
          "level": null,
          "query": "上海静安寺街道南京西路1618号久光百货B1FDB17-19(近静安寺)",
          "source": "amap_js_browser",
          "geocoded_at": "2026-06-13T11:26:12.496Z"
        }
      },
      "offers": [],
      "extraction": {
        "status": "ok",
        "details_hidden": false,
        "captured_at": "2026-06-13T09:20:41.737Z",
        "method": "codex-extension",
        "elapsed_ms": 804
      }
    },
    {
      "scan_id": "2026-06-13T09:20:25.047Z",
      "source": {
        "base_url": "https://www.dianping.com/shanghai/ch10/r101937",
        "page_url": "https://www.dianping.com/shanghai/ch10/r101937d500p2",
        "page_number": 2,
        "result_index": 1
      },
      "shop": {
        "name": "南伶(静安嘉里店)",
        "url": "https://www.dianping.com/shop/k3M6Jq1msRnpoFkI",
        "shop_id": "k3M6Jq1msRnpoFkI",
        "image_url": "http://p0.meituan.net/biztone/380901_1661158120322.jpeg%40340w_255h_1e_1c_1l%7Cwatermark%3D0",
        "name_pinyin": "nan ling ( jing an jia li dian )",
        "address": "南京西路1515号静安嘉里中心南区3楼S3-01",
        "address_pinyin": "nan jing xi lu 1515 hao jing an jia li zhong xin nan qu 3 lou S3-01",
        "rating": 4.3,
        "review_count": 6002,
        "avg_price_per_person": 188,
        "area": null,
        "category": "静安寺商圈淮扬菜",
        "score_breakdown": {
          "口味": 4.3,
          "环境": 4.4,
          "服务": 4.3
        },
        "ranking_badge": "静安区淮扬菜热门榜 · 第10名",
        "open_status": "休息中",
        "opening_hours": "11:00-14:00, 17:30-21:00",
        "distance_from_station": {
          "raw_text": "距地铁7号线静安寺站6口步行170m",
          "transit_text": "7号线静安寺站6口",
          "walking_distance_meters": 170
        },
        "amenities": [
          "有大桌",
          "付费停车"
        ],
        "recommended_dishes": [
          "葱油鸡",
          "南伶烤鸭",
          "蟹粉狮子头",
          "苔条拖黄鱼",
          "扬州干丝烫头",
          "豆沙锅饼",
          "油爆河虾",
          "响油鳝糊",
          "千层油糕",
          "土豆沙拉"
        ],
        "menu_count": 46,
        "review_section_count": null,
        "amap_location": {
          "lng": 121.449257,
          "lat": 31.223167,
          "formatted_address": null,
          "level": null,
          "query": "上海南京西路1515号静安嘉里中心南区3楼S3-01",
          "source": "amap_js_browser",
          "geocoded_at": "2026-06-13T11:26:12.496Z"
        }
      },
      "offers": [
        {
          "type": "voucher",
          "title": "指定商品可用",
          "price": 95,
          "currency": "CNY",
          "discount": "9.5折",
          "original_price": null,
          "flags": [
            "随时退",
            "过期自动退"
          ],
          "details": {
            "group_size": null,
            "valid_time": null,
            "earliest_usable": null
          },
          "raw_text": "指定商品可用 随时退 过期自动退 ¥ 95 9.5折 买券",
          "image_url": null
        }
      ],
      "extraction": {
        "status": "ok",
        "details_hidden": false,
        "captured_at": "2026-06-13T09:20:42.528Z",
        "method": "codex-extension",
        "elapsed_ms": 788
      }
    },
    {
      "scan_id": "2026-06-13T09:20:25.047Z",
      "source": {
        "base_url": "https://www.dianping.com/shanghai/ch10/r101937",
        "page_url": "https://www.dianping.com/shanghai/ch10/r101937d500p2",
        "page_number": 2,
        "result_index": 2
      },
      "shop": {
        "name": "悠乐DeliCake·咸奶油 轻糖蛋糕(静安久光百货店)",
        "url": "https://www.dianping.com/shop/ka6f6SygLYQGPypK",
        "shop_id": "ka6f6SygLYQGPypK",
        "image_url": "https://img.meituan.net/content/d807745f6fe5a3b2a48f6b6b95f32827140558.jpg%40340w_255h_1e_1c_1l%7Cwatermark%3D0",
        "name_pinyin": "you le DeliCake· xian nai you qing tang dan gao ( jing an jiu guang bai huo dian )",
        "address": null,
        "address_pinyin": null,
        "rating": null,
        "review_count": null,
        "avg_price_per_person": null,
        "area": null,
        "category": null,
        "score_breakdown": null,
        "ranking_badge": null,
        "open_status": null,
        "opening_hours": null,
        "distance_from_station": null,
        "amenities": [],
        "recommended_dishes": [],
        "menu_count": null,
        "review_section_count": null
      },
      "offers": [],
      "extraction": {
        "status": "ok",
        "details_hidden": false,
        "captured_at": "2026-06-13T09:20:42.909Z",
        "method": "codex-extension",
        "elapsed_ms": 377
      }
    },
    {
      "scan_id": "2026-06-13T09:20:25.047Z",
      "source": {
        "base_url": "https://www.dianping.com/shanghai/ch10/r101937",
        "page_url": "https://www.dianping.com/shanghai/ch10/r101937d500p2",
        "page_number": 2,
        "result_index": 3
      },
      "shop": {
        "name": "Calypso地中海餐厅·酒廊(静安香格里拉店)",
        "url": "https://www.dianping.com/shop/H8iuroAMltleVA1F",
        "shop_id": "H8iuroAMltleVA1F",
        "image_url": "https://img.meituan.net/content/1e2c422c6f6be74ed0789675104e4e20360620.jpg%40340w_255h_1e_1c_1l%7Cwatermark%3D0",
        "name_pinyin": "Calypso di zhong hai can ting · jiu lang ( jing an xiang ge li la dian )",
        "address": null,
        "address_pinyin": null,
        "rating": null,
        "review_count": null,
        "avg_price_per_person": null,
        "area": null,
        "category": null,
        "score_breakdown": null,
        "ranking_badge": null,
        "open_status": null,
        "opening_hours": null,
        "distance_from_station": null,
        "amenities": [],
        "recommended_dishes": [],
        "menu_count": null,
        "review_section_count": null
      },
      "offers": [],
      "extraction": {
        "status": "ok",
        "details_hidden": false,
        "captured_at": "2026-06-13T09:20:43.279Z",
        "method": "codex-extension",
        "elapsed_ms": 362
      }
    },
    {
      "scan_id": "2026-06-13T09:20:25.047Z",
      "source": {
        "base_url": "https://www.dianping.com/shanghai/ch10/r101937",
        "page_url": "https://www.dianping.com/shanghai/ch10/r101937d500p2",
        "page_number": 2,
        "result_index": 4
      },
      "shop": {
        "name": "竹若金枪鱼(静安寺店)",
        "url": "https://www.dianping.com/shop/G5NeF0ocxf9QfWPH",
        "shop_id": "G5NeF0ocxf9QfWPH",
        "image_url": "https://img.meituan.net/content/a70b3d30e38296c09083ac9fed7a76ce154524.jpg%40340w_255h_1e_1c_1l%7Cwatermark%3D0",
        "name_pinyin": "zhu ruo jin qiang yu ( jing an si dian )",
        "address": null,
        "address_pinyin": null,
        "rating": null,
        "review_count": null,
        "avg_price_per_person": null,
        "area": null,
        "category": null,
        "score_breakdown": null,
        "ranking_badge": null,
        "open_status": null,
        "opening_hours": null,
        "distance_from_station": null,
        "amenities": [],
        "recommended_dishes": [],
        "menu_count": null,
        "review_section_count": null
      },
      "offers": [],
      "extraction": {
        "status": "ok",
        "details_hidden": false,
        "captured_at": "2026-06-13T09:20:43.653Z",
        "method": "codex-extension",
        "elapsed_ms": 370
      }
    },
    {
      "scan_id": "2026-06-13T09:20:25.047Z",
      "source": {
        "base_url": "https://www.dianping.com/shanghai/ch10/r101937",
        "page_url": "https://www.dianping.com/shanghai/ch10/r101937d500p2",
        "page_number": 2,
        "result_index": 5
      },
      "shop": {
        "name": "夏小馆·夏宫中餐厅(静安香格里拉店)",
        "url": "https://www.dianping.com/shop/l6kCMdMshRlYr3SI",
        "shop_id": "l6kCMdMshRlYr3SI",
        "image_url": "https://img.meituan.net/content/ef55ffe9b75459f9ab3a5b1227ba8a7b502530.jpg%40340w_255h_1e_1c_1l%7Cwatermark%3D0",
        "name_pinyin": "xia xiao guan · xia gong zhong can ting ( jing an xiang ge li la dian )",
        "address": null,
        "address_pinyin": null,
        "rating": null,
        "review_count": null,
        "avg_price_per_person": null,
        "area": null,
        "category": null,
        "score_breakdown": null,
        "ranking_badge": null,
        "open_status": null,
        "opening_hours": null,
        "distance_from_station": null,
        "amenities": [],
        "recommended_dishes": [],
        "menu_count": null,
        "review_section_count": null
      },
      "offers": [],
      "extraction": {
        "status": "ok",
        "details_hidden": false,
        "captured_at": "2026-06-13T09:20:44.002Z",
        "method": "codex-extension",
        "elapsed_ms": 345
      }
    },
    {
      "scan_id": "2026-06-13T09:20:25.047Z",
      "source": {
        "base_url": "https://www.dianping.com/shanghai/ch10/r101937",
        "page_url": "https://www.dianping.com/shanghai/ch10/r101937d500p2",
        "page_number": 2,
        "result_index": 6
      },
      "shop": {
        "name": "风景菜韩国无限量烤肉(静安店)",
        "url": "https://www.dianping.com/shop/H4umnxLPAs7OBMWh",
        "shop_id": "H4umnxLPAs7OBMWh",
        "image_url": "http://p0.meituan.net/biztone/66f32be2d49b72a929594b6e5a9e90c0441719.jpg%40340w_255h_1e_1c_1l%7Cwatermark%3D0",
        "name_pinyin": "feng jing cai han guo wu xian liang kao rou ( jing an dian )",
        "address": null,
        "address_pinyin": null,
        "rating": null,
        "review_count": null,
        "avg_price_per_person": null,
        "area": null,
        "category": null,
        "score_breakdown": null,
        "ranking_badge": null,
        "open_status": null,
        "opening_hours": null,
        "distance_from_station": null,
        "amenities": [],
        "recommended_dishes": [],
        "menu_count": null,
        "review_section_count": null
      },
      "offers": [],
      "extraction": {
        "status": "ok",
        "details_hidden": false,
        "captured_at": "2026-06-13T09:20:44.347Z",
        "method": "codex-extension",
        "elapsed_ms": 342
      }
    },
    {
      "scan_id": "2026-06-13T09:20:25.047Z",
      "source": {
        "base_url": "https://www.dianping.com/shanghai/ch10/r101937",
        "page_url": "https://www.dianping.com/shanghai/ch10/r101937d500p2",
        "page_number": 2,
        "result_index": 7
      },
      "shop": {
        "name": "潮堂 · 潮州菜(久光店)",
        "url": "https://www.dianping.com/shop/k5ZCibkzmX2t2ISV",
        "shop_id": "k5ZCibkzmX2t2ISV",
        "image_url": "https://img.meituan.net/content/9a783f6e0168da57c3175ea934ec882c2025893.png%40340w_255h_1e_1c_1l%7Cwatermark%3D0",
        "name_pinyin": "chao tang · chao zhou cai ( jiu guang dian )",
        "address": null,
        "address_pinyin": null,
        "rating": null,
        "review_count": null,
        "avg_price_per_person": null,
        "area": null,
        "category": null,
        "score_breakdown": null,
        "ranking_badge": null,
        "open_status": null,
        "opening_hours": null,
        "distance_from_station": null,
        "amenities": [],
        "recommended_dishes": [],
        "menu_count": null,
        "review_section_count": null
      },
      "offers": [],
      "extraction": {
        "status": "ok",
        "details_hidden": false,
        "captured_at": "2026-06-13T09:20:44.759Z",
        "method": "codex-extension",
        "elapsed_ms": 409
      }
    },
    {
      "scan_id": "2026-06-13T09:20:25.047Z",
      "source": {
        "base_url": "https://www.dianping.com/shanghai/ch10/r101937",
        "page_url": "https://www.dianping.com/shanghai/ch10/r101937d500p2",
        "page_number": 2,
        "result_index": 8
      },
      "shop": {
        "name": "逸谷会(静安嘉里中心店)",
        "url": "https://www.dianping.com/shop/i62KGdWIB8XoCAC8",
        "shop_id": "i62KGdWIB8XoCAC8",
        "image_url": "https://img.meituan.net/content/b05d7f1580d9535d9a6cbec1d61a057051127.jpg%40340w_255h_1e_1c_1l%7Cwatermark%3D0",
        "name_pinyin": "yi gu hui ( jing an jia li zhong xin dian )",
        "address": null,
        "address_pinyin": null,
        "rating": null,
        "review_count": null,
        "avg_price_per_person": null,
        "area": null,
        "category": null,
        "score_breakdown": null,
        "ranking_badge": null,
        "open_status": null,
        "opening_hours": null,
        "distance_from_station": null,
        "amenities": [],
        "recommended_dishes": [],
        "menu_count": null,
        "review_section_count": null
      },
      "offers": [],
      "extraction": {
        "status": "ok",
        "details_hidden": false,
        "captured_at": "2026-06-13T09:20:45.161Z",
        "method": "codex-extension",
        "elapsed_ms": 398
      }
    },
    {
      "scan_id": "2026-06-13T09:20:25.047Z",
      "source": {
        "base_url": "https://www.dianping.com/shanghai/ch10/r101937",
        "page_url": "https://www.dianping.com/shanghai/ch10/r101937d500p2",
        "page_number": 2,
        "result_index": 9
      },
      "shop": {
        "name": "老吉士(久光店)",
        "url": "https://www.dianping.com/shop/l9SzGpFIIZDqFOvR",
        "shop_id": "l9SzGpFIIZDqFOvR",
        "image_url": "http://p0.meituan.net/biztone/5170298_1680572680589.jpeg%40340w_255h_1e_1c_1l%7Cwatermark%3D0",
        "name_pinyin": "lao ji shi ( jiu guang dian )",
        "address": null,
        "address_pinyin": null,
        "rating": null,
        "review_count": null,
        "avg_price_per_person": null,
        "area": null,
        "category": null,
        "score_breakdown": null,
        "ranking_badge": null,
        "open_status": null,
        "opening_hours": null,
        "distance_from_station": null,
        "amenities": [],
        "recommended_dishes": [],
        "menu_count": null,
        "review_section_count": null
      },
      "offers": [],
      "extraction": {
        "status": "ok",
        "details_hidden": false,
        "captured_at": "2026-06-13T09:20:45.554Z",
        "method": "codex-extension",
        "elapsed_ms": 390
      }
    },
    {
      "scan_id": "2026-06-13T09:20:25.047Z",
      "source": {
        "base_url": "https://www.dianping.com/shanghai/ch10/r101937",
        "page_url": "https://www.dianping.com/shanghai/ch10/r101937d500p2",
        "page_number": 2,
        "result_index": 10
      },
      "shop": {
        "name": "布歌东京(久光百货店)",
        "url": "https://www.dianping.com/shop/l70gQ7Zf5bDomCYf",
        "shop_id": "l70gQ7Zf5bDomCYf",
        "image_url": "https://img.meituan.net/content/5bf498086a37084e096907a0411ab13966208.jpg%40340w_255h_1e_1c_1l%7Cwatermark%3D0",
        "name_pinyin": "bu ge dong jing ( jiu guang bai huo dian )",
        "address": null,
        "address_pinyin": null,
        "rating": null,
        "review_count": null,
        "avg_price_per_person": null,
        "area": null,
        "category": null,
        "score_breakdown": null,
        "ranking_badge": null,
        "open_status": null,
        "opening_hours": null,
        "distance_from_station": null,
        "amenities": [],
        "recommended_dishes": [],
        "menu_count": null,
        "review_section_count": null
      },
      "offers": [],
      "extraction": {
        "status": "ok",
        "details_hidden": false,
        "captured_at": "2026-06-13T09:20:45.950Z",
        "method": "codex-extension",
        "elapsed_ms": 391
      }
    },
    {
      "scan_id": "2026-06-13T09:20:25.047Z",
      "source": {
        "base_url": "https://www.dianping.com/shanghai/ch10/r101937",
        "page_url": "https://www.dianping.com/shanghai/ch10/r101937d500p2",
        "page_number": 2,
        "result_index": 11
      },
      "shop": {
        "name": "圆苑(静安寺店)",
        "url": "https://www.dianping.com/shop/lawBW43ZmFjtZA6X",
        "shop_id": "lawBW43ZmFjtZA6X",
        "image_url": "https://img.meituan.net/content/3a70940ae56f04c285ae7acad37b9ce4319251.jpg%40340w_255h_1e_1c_1l%7Cwatermark%3D0",
        "name_pinyin": "yuan yuan ( jing an si dian )",
        "address": null,
        "address_pinyin": null,
        "rating": null,
        "review_count": null,
        "avg_price_per_person": null,
        "area": null,
        "category": null,
        "score_breakdown": null,
        "ranking_badge": null,
        "open_status": null,
        "opening_hours": null,
        "distance_from_station": null,
        "amenities": [],
        "recommended_dishes": [],
        "menu_count": null,
        "review_section_count": null
      },
      "offers": [],
      "extraction": {
        "status": "ok",
        "details_hidden": false,
        "captured_at": "2026-06-13T09:20:46.352Z",
        "method": "codex-extension",
        "elapsed_ms": 395
      }
    },
    {
      "scan_id": "2026-06-13T09:20:25.047Z",
      "source": {
        "base_url": "https://www.dianping.com/shanghai/ch10/r101937",
        "page_url": "https://www.dianping.com/shanghai/ch10/r101937d500p2",
        "page_number": 2,
        "result_index": 12
      },
      "shop": {
        "name": "平成屋·Late Night食堂(愚园路店)",
        "url": "https://www.dianping.com/shop/l2lFjTBzbtDmrTHf",
        "shop_id": "l2lFjTBzbtDmrTHf",
        "image_url": "http://p1.meituan.net/biztone/92296a88ed770278da569cf2303a5a83255875.jpg%40340w_255h_1e_1c_1l%7Cwatermark%3D0",
        "name_pinyin": "ping cheng wu ·Late Night shi tang ( yu yuan lu dian )",
        "address": null,
        "address_pinyin": null,
        "rating": null,
        "review_count": null,
        "avg_price_per_person": null,
        "area": null,
        "category": null,
        "score_breakdown": null,
        "ranking_badge": null,
        "open_status": null,
        "opening_hours": null,
        "distance_from_station": null,
        "amenities": [],
        "recommended_dishes": [],
        "menu_count": null,
        "review_section_count": null
      },
      "offers": [],
      "extraction": {
        "status": "ok",
        "details_hidden": false,
        "captured_at": "2026-06-13T09:20:46.712Z",
        "method": "codex-extension",
        "elapsed_ms": 356
      }
    },
    {
      "scan_id": "2026-06-13T09:20:25.047Z",
      "source": {
        "base_url": "https://www.dianping.com/shanghai/ch10/r101937",
        "page_url": "https://www.dianping.com/shanghai/ch10/r101937d500p2",
        "page_number": 2,
        "result_index": 13
      },
      "shop": {
        "name": "我家餐厅(华山路店)",
        "url": "https://www.dianping.com/shop/G84UxG7AwrhpXdsL",
        "shop_id": "G84UxG7AwrhpXdsL",
        "image_url": "http://qcloud.dpfile.com/pc/E53tFbOpSpnOHa4ndyByZ3To8Jq_fhUsZp5od1NrU4ZbABLJ-NMpmWgYt00SYGDobKcq9vnEaGy3xLEf-_v_oA.jpg",
        "name_pinyin": "wo jia can ting ( hua shan lu dian )",
        "address": null,
        "address_pinyin": null,
        "rating": null,
        "review_count": null,
        "avg_price_per_person": null,
        "area": null,
        "category": null,
        "score_breakdown": null,
        "ranking_badge": null,
        "open_status": null,
        "opening_hours": null,
        "distance_from_station": null,
        "amenities": [],
        "recommended_dishes": [],
        "menu_count": null,
        "review_section_count": null
      },
      "offers": [],
      "extraction": {
        "status": "ok",
        "details_hidden": false,
        "captured_at": "2026-06-13T09:20:47.057Z",
        "method": "codex-extension",
        "elapsed_ms": 340
      }
    },
    {
      "scan_id": "2026-06-13T09:20:25.047Z",
      "source": {
        "base_url": "https://www.dianping.com/shanghai/ch10/r101937",
        "page_url": "https://www.dianping.com/shanghai/ch10/r101937d500p2",
        "page_number": 2,
        "result_index": 14
      },
      "shop": {
        "name": "拉蒂娜·巴西牛排馆 Latina·Brazilian Steakhouse(铜...",
        "url": "https://www.dianping.com/shop/H9hmJZb9RIJ43JBS",
        "shop_id": "H9hmJZb9RIJ43JBS",
        "image_url": "https://img.meituan.net/content/e2fd0c70fc3819dc7c25baa0e97dd585233602.jpg%40340w_255h_1e_1c_1l%7Cwatermark%3D0",
        "name_pinyin": "la di na · ba xi niu pai guan Latina·Brazilian Steakhouse( tong ...",
        "address": null,
        "address_pinyin": null,
        "rating": null,
        "review_count": null,
        "avg_price_per_person": null,
        "area": null,
        "category": null,
        "score_breakdown": null,
        "ranking_badge": null,
        "open_status": null,
        "opening_hours": null,
        "distance_from_station": null,
        "amenities": [],
        "recommended_dishes": [],
        "menu_count": null,
        "review_section_count": null
      },
      "offers": [],
      "extraction": {
        "status": "ok",
        "details_hidden": false,
        "captured_at": "2026-06-13T09:20:47.420Z",
        "method": "codex-extension",
        "elapsed_ms": 359
      }
    },
    {
      "scan_id": "2026-06-13T09:20:25.047Z",
      "source": {
        "base_url": "https://www.dianping.com/shanghai/ch10/r101937",
        "page_url": "https://www.dianping.com/shanghai/ch10/r101937d500p2",
        "page_number": 2,
        "result_index": 15
      },
      "shop": {
        "name": "夏宫中餐厅(静安香格里拉店)",
        "url": "https://www.dianping.com/shop/l6jHMBtmK7D4drZt",
        "shop_id": "l6jHMBtmK7D4drZt",
        "image_url": "https://img.meituan.net/content/4bbb855a50ab1e2e2642efb38badc43c309042.jpg%40340w_255h_1e_1c_1l%7Cwatermark%3D0",
        "name_pinyin": "xia gong zhong can ting ( jing an xiang ge li la dian )",
        "address": null,
        "address_pinyin": null,
        "rating": null,
        "review_count": null,
        "avg_price_per_person": null,
        "area": null,
        "category": null,
        "score_breakdown": null,
        "ranking_badge": null,
        "open_status": null,
        "opening_hours": null,
        "distance_from_station": null,
        "amenities": [],
        "recommended_dishes": [],
        "menu_count": null,
        "review_section_count": null
      },
      "offers": [],
      "extraction": {
        "status": "ok",
        "details_hidden": false,
        "captured_at": "2026-06-13T09:20:47.808Z",
        "method": "codex-extension",
        "elapsed_ms": 385
      }
    },
    {
      "scan_id": "2026-06-13T09:20:25.047Z",
      "source": {
        "base_url": "https://www.dianping.com/shanghai/ch10/r101937",
        "page_url": "https://www.dianping.com/shanghai/ch10/r101937d500p3",
        "page_number": 3,
        "result_index": 1
      },
      "shop": {
        "name": "醉东Oriental House(静安嘉里中心店)",
        "url": "https://www.dianping.com/shop/l1pFxEUMxhYPVMz7",
        "shop_id": "l1pFxEUMxhYPVMz7",
        "image_url": "https://img.meituan.net/content/d970416c034bb70c29b7e5dfda5e3ab369855.jpg%40340w_255h_1e_1c_1l%7Cwatermark%3D0",
        "name_pinyin": "zui dong Oriental House( jing an jia li zhong xin dian )",
        "address": null,
        "address_pinyin": null,
        "rating": null,
        "review_count": null,
        "avg_price_per_person": null,
        "area": null,
        "category": null,
        "score_breakdown": null,
        "ranking_badge": null,
        "open_status": null,
        "opening_hours": null,
        "distance_from_station": null,
        "amenities": [],
        "recommended_dishes": [],
        "menu_count": null,
        "review_section_count": null
      },
      "offers": [],
      "extraction": {
        "status": "ok",
        "details_hidden": false,
        "captured_at": "2026-06-13T09:20:48.190Z",
        "method": "codex-extension",
        "elapsed_ms": 378
      }
    },
    {
      "scan_id": "2026-06-13T09:20:25.047Z",
      "source": {
        "base_url": "https://www.dianping.com/shanghai/ch10/r101937",
        "page_url": "https://www.dianping.com/shanghai/ch10/r101937d500p3",
        "page_number": 3,
        "result_index": 2
      },
      "shop": {
        "name": "Spread the Bagel·CinnaSwirl(静安寺店)",
        "url": "https://www.dianping.com/shop/l9Kmj99IoTUHvcnZ",
        "shop_id": "l9Kmj99IoTUHvcnZ",
        "image_url": "https://img.meituan.net/content/358188baee163c7d1b7cb66427f2af1c157452.jpg%40340w_255h_1e_1c_1l%7Cwatermark%3D0",
        "name_pinyin": "Spread the Bagel·CinnaSwirl( jing an si dian )",
        "address": null,
        "address_pinyin": null,
        "rating": null,
        "review_count": null,
        "avg_price_per_person": null,
        "area": null,
        "category": null,
        "score_breakdown": null,
        "ranking_badge": null,
        "open_status": null,
        "opening_hours": null,
        "distance_from_station": null,
        "amenities": [],
        "recommended_dishes": [],
        "menu_count": null,
        "review_section_count": null
      },
      "offers": [],
      "extraction": {
        "status": "ok",
        "details_hidden": false,
        "captured_at": "2026-06-13T09:20:48.527Z",
        "method": "codex-extension",
        "elapsed_ms": 334
      }
    },
    {
      "scan_id": "2026-06-13T09:20:25.047Z",
      "source": {
        "base_url": "https://www.dianping.com/shanghai/ch10/r101937",
        "page_url": "https://www.dianping.com/shanghai/ch10/r101937d500p3",
        "page_number": 3,
        "result_index": 3
      },
      "shop": {
        "name": "阿吾罗日本料理(芮欧百货店)",
        "url": "https://www.dianping.com/shop/H8Y2PqxYAJpkqohA",
        "shop_id": "H8Y2PqxYAJpkqohA",
        "image_url": "https://img.meituan.net/content/e2cbc540c4c324e814ac86dd4024901384837.jpg%40340w_255h_1e_1c_1l%7Cwatermark%3D0",
        "name_pinyin": "a wu luo ri ben liao li ( rui ou bai huo dian )",
        "address": null,
        "address_pinyin": null,
        "rating": null,
        "review_count": null,
        "avg_price_per_person": null,
        "area": null,
        "category": null,
        "score_breakdown": null,
        "ranking_badge": null,
        "open_status": null,
        "opening_hours": null,
        "distance_from_station": null,
        "amenities": [],
        "recommended_dishes": [],
        "menu_count": null,
        "review_section_count": null
      },
      "offers": [],
      "extraction": {
        "status": "ok",
        "details_hidden": false,
        "captured_at": "2026-06-13T09:20:48.976Z",
        "method": "codex-extension",
        "elapsed_ms": 444
      }
    },
    {
      "scan_id": "2026-06-13T09:20:25.047Z",
      "source": {
        "base_url": "https://www.dianping.com/shanghai/ch10/r101937",
        "page_url": "https://www.dianping.com/shanghai/ch10/r101937d500p3",
        "page_number": 3,
        "result_index": 4
      },
      "shop": {
        "name": "吉品小鲜Jhouse(静安店)",
        "url": "https://www.dianping.com/shop/H81LavpjYK8FYkeM",
        "shop_id": "H81LavpjYK8FYkeM",
        "image_url": "https://img.meituan.net/content/079431ddcdaa3ca4937ac8cd3040a3e6390749.jpg%40340w_255h_1e_1c_1l%7Cwatermark%3D0",
        "name_pinyin": "ji pin xiao xian Jhouse( jing an dian )",
        "address": null,
        "address_pinyin": null,
        "rating": null,
        "review_count": null,
        "avg_price_per_person": null,
        "area": null,
        "category": null,
        "score_breakdown": null,
        "ranking_badge": null,
        "open_status": null,
        "opening_hours": null,
        "distance_from_station": null,
        "amenities": [],
        "recommended_dishes": [],
        "menu_count": null,
        "review_section_count": null
      },
      "offers": [],
      "extraction": {
        "status": "ok",
        "details_hidden": false,
        "captured_at": "2026-06-13T09:20:49.366Z",
        "method": "codex-extension",
        "elapsed_ms": 386
      }
    },
    {
      "scan_id": "2026-06-13T09:20:25.047Z",
      "source": {
        "base_url": "https://www.dianping.com/shanghai/ch10/r101937",
        "page_url": "https://www.dianping.com/shanghai/ch10/r101937d500p3",
        "page_number": 3,
        "result_index": 5
      },
      "shop": {
        "name": "PokeX(静安寺店)",
        "url": "https://www.dianping.com/shop/l14NvT3Incj4Cgar",
        "shop_id": "l14NvT3Incj4Cgar",
        "image_url": "http://p0.meituan.net/biztone/d0b557db3bb0f2fea02d82d125066cb2457575.jpg%40340w_255h_1e_1c_1l%7Cwatermark%3D0",
        "name_pinyin": "PokeX( jing an si dian )",
        "address": null,
        "address_pinyin": null,
        "rating": null,
        "review_count": null,
        "avg_price_per_person": null,
        "area": null,
        "category": null,
        "score_breakdown": null,
        "ranking_badge": null,
        "open_status": null,
        "opening_hours": null,
        "distance_from_station": null,
        "amenities": [],
        "recommended_dishes": [],
        "menu_count": null,
        "review_section_count": null
      },
      "offers": [],
      "extraction": {
        "status": "ok",
        "details_hidden": false,
        "captured_at": "2026-06-13T09:20:49.752Z",
        "method": "codex-extension",
        "elapsed_ms": 382
      }
    },
    {
      "scan_id": "2026-06-13T09:20:25.047Z",
      "source": {
        "base_url": "https://www.dianping.com/shanghai/ch10/r101937",
        "page_url": "https://www.dianping.com/shanghai/ch10/r101937d500p3",
        "page_number": 3,
        "result_index": 6
      },
      "shop": {
        "name": "Shake Shack(静安嘉里中心店)",
        "url": "https://www.dianping.com/shop/l8A1Fe8moJT7yzgh",
        "shop_id": "l8A1Fe8moJT7yzgh",
        "image_url": "https://img.meituan.net/content/0c11d6102b59c77dde97c52d15188ac238159.jpg%40340w_255h_1e_1c_1l%7Cwatermark%3D0",
        "name_pinyin": "Shake Shack( jing an jia li zhong xin dian )",
        "address": null,
        "address_pinyin": null,
        "rating": null,
        "review_count": null,
        "avg_price_per_person": null,
        "area": null,
        "category": null,
        "score_breakdown": null,
        "ranking_badge": null,
        "open_status": null,
        "opening_hours": null,
        "distance_from_station": null,
        "amenities": [],
        "recommended_dishes": [],
        "menu_count": null,
        "review_section_count": null
      },
      "offers": [],
      "extraction": {
        "status": "ok",
        "details_hidden": false,
        "captured_at": "2026-06-13T09:20:50.090Z",
        "method": "codex-extension",
        "elapsed_ms": 335
      }
    },
    {
      "scan_id": "2026-06-13T09:20:25.047Z",
      "source": {
        "base_url": "https://www.dianping.com/shanghai/ch10/r101937",
        "page_url": "https://www.dianping.com/shanghai/ch10/r101937d500p3",
        "page_number": 3,
        "result_index": 7
      },
      "shop": {
        "name": "两咖啡自助餐厅(静安香格里拉酒店)",
        "url": "https://www.dianping.com/shop/H5LE8cUAt2sHZGof",
        "shop_id": "H5LE8cUAt2sHZGof",
        "image_url": "http://p1.meituan.net/biztone/4934209_1641293339292.jpeg%40340w_255h_1e_1c_1l%7Cwatermark%3D0",
        "name_pinyin": "liang ka fei zi zhu can ting ( jing an xiang ge li la jiu dian )",
        "address": null,
        "address_pinyin": null,
        "rating": null,
        "review_count": null,
        "avg_price_per_person": null,
        "area": null,
        "category": null,
        "score_breakdown": null,
        "ranking_badge": null,
        "open_status": null,
        "opening_hours": null,
        "distance_from_station": null,
        "amenities": [],
        "recommended_dishes": [],
        "menu_count": null,
        "review_section_count": null
      },
      "offers": [],
      "extraction": {
        "status": "ok",
        "details_hidden": false,
        "captured_at": "2026-06-13T09:20:50.426Z",
        "method": "codex-extension",
        "elapsed_ms": 332
      }
    },
    {
      "scan_id": "2026-06-13T09:20:25.047Z",
      "source": {
        "base_url": "https://www.dianping.com/shanghai/ch10/r101937",
        "page_url": "https://www.dianping.com/shanghai/ch10/r101937d500p3",
        "page_number": 3,
        "result_index": 8
      },
      "shop": {
        "name": "六月半湖南湘鲜馆(嘉里中心店)",
        "url": "https://www.dianping.com/shop/l9gt8BbJyBlRzd1z",
        "shop_id": "l9gt8BbJyBlRzd1z",
        "image_url": "https://img.meituan.net/content/0db608902fc9b7fed09ed6cc2c127f1b157770.jpg%40340w_255h_1e_1c_1l%7Cwatermark%3D0",
        "name_pinyin": "liu yue ban hu nan xiang xian guan ( jia li zhong xin dian )",
        "address": null,
        "address_pinyin": null,
        "rating": null,
        "review_count": null,
        "avg_price_per_person": null,
        "area": null,
        "category": null,
        "score_breakdown": null,
        "ranking_badge": null,
        "open_status": null,
        "opening_hours": null,
        "distance_from_station": null,
        "amenities": [],
        "recommended_dishes": [],
        "menu_count": null,
        "review_section_count": null
      },
      "offers": [],
      "extraction": {
        "status": "ok",
        "details_hidden": false,
        "captured_at": "2026-06-13T09:20:50.802Z",
        "method": "codex-extension",
        "elapsed_ms": 372
      }
    },
    {
      "scan_id": "2026-06-13T09:20:25.047Z",
      "source": {
        "base_url": "https://www.dianping.com/shanghai/ch10/r101937",
        "page_url": "https://www.dianping.com/shanghai/ch10/r101937d500p3",
        "page_number": 3,
        "result_index": 9
      },
      "shop": {
        "name": "静安小亭(万航渡路店)",
        "url": "https://www.dianping.com/shop/l1ldHN7VMZ8n8XSm",
        "shop_id": "l1ldHN7VMZ8n8XSm",
        "image_url": "http://qcloud.dpfile.com/pc/Q2Ygv_POieQedC-WsCMeBSQYVIYsnlhmOboxfQP7tcCIwwaR8s_WYruHjDqJ5KVGbKcq9vnEaGy3xLEf-_v_oA.jpg",
        "name_pinyin": "jing an xiao ting ( wan hang du lu dian )",
        "address": null,
        "address_pinyin": null,
        "rating": null,
        "review_count": null,
        "avg_price_per_person": null,
        "area": null,
        "category": null,
        "score_breakdown": null,
        "ranking_badge": null,
        "open_status": null,
        "opening_hours": null,
        "distance_from_station": null,
        "amenities": [],
        "recommended_dishes": [],
        "menu_count": null,
        "review_section_count": null
      },
      "offers": [],
      "extraction": {
        "status": "ok",
        "details_hidden": false,
        "captured_at": "2026-06-13T09:20:51.222Z",
        "method": "codex-extension",
        "elapsed_ms": 415
      }
    },
    {
      "scan_id": "2026-06-13T09:20:25.047Z",
      "source": {
        "base_url": "https://www.dianping.com/shanghai/ch10/r101937",
        "page_url": "https://www.dianping.com/shanghai/ch10/r101937d500p3",
        "page_number": 3,
        "result_index": 10
      },
      "shop": {
        "name": "佳家汤包(CP静安店)",
        "url": "https://www.dianping.com/shop/l56NGSE0cPQce4dz",
        "shop_id": "l56NGSE0cPQce4dz",
        "image_url": "http://p0.meituan.net/biztone/5903c8d89248846d83e2d65307258a80372746.jpg%40340w_255h_1e_1c_1l%7Cwatermark%3D0",
        "name_pinyin": "jia jia tang bao (CP jing an dian )",
        "address": null,
        "address_pinyin": null,
        "rating": null,
        "review_count": null,
        "avg_price_per_person": null,
        "area": null,
        "category": null,
        "score_breakdown": null,
        "ranking_badge": null,
        "open_status": null,
        "opening_hours": null,
        "distance_from_station": null,
        "amenities": [],
        "recommended_dishes": [],
        "menu_count": null,
        "review_section_count": null
      },
      "offers": [],
      "extraction": {
        "status": "ok",
        "details_hidden": false,
        "captured_at": "2026-06-13T09:20:51.607Z",
        "method": "codex-extension",
        "elapsed_ms": 381
      }
    },
    {
      "scan_id": "2026-06-13T09:20:25.047Z",
      "source": {
        "base_url": "https://www.dianping.com/shanghai/ch10/r101937",
        "page_url": "https://www.dianping.com/shanghai/ch10/r101937d500p3",
        "page_number": 3,
        "result_index": 11
      },
      "shop": {
        "name": "松发肉骨茶SongFa(静安嘉里中心店)",
        "url": "https://www.dianping.com/shop/ka1giNOvRr0zXcv1",
        "shop_id": "ka1giNOvRr0zXcv1",
        "image_url": "https://img.meituan.net/content/abe9270cd833fe5788a21d20d442873888169.jpg%40340w_255h_1e_1c_1l%7Cwatermark%3D0",
        "name_pinyin": "song fa rou gu cha SongFa( jing an jia li zhong xin dian )",
        "address": null,
        "address_pinyin": null,
        "rating": null,
        "review_count": null,
        "avg_price_per_person": null,
        "area": null,
        "category": null,
        "score_breakdown": null,
        "ranking_badge": null,
        "open_status": null,
        "opening_hours": null,
        "distance_from_station": null,
        "amenities": [],
        "recommended_dishes": [],
        "menu_count": null,
        "review_section_count": null
      },
      "offers": [],
      "extraction": {
        "status": "ok",
        "details_hidden": false,
        "captured_at": "2026-06-13T09:20:52.009Z",
        "method": "codex-extension",
        "elapsed_ms": 399
      }
    },
    {
      "scan_id": "2026-06-13T09:20:25.047Z",
      "source": {
        "base_url": "https://www.dianping.com/shanghai/ch10/r101937",
        "page_url": "https://www.dianping.com/shanghai/ch10/r101937d500p3",
        "page_number": 3,
        "result_index": 12
      },
      "shop": {
        "name": "DOE coffee(铜仁路店)",
        "url": "https://www.dianping.com/shop/l3amuH8On9rcWpyi",
        "shop_id": "l3amuH8On9rcWpyi",
        "image_url": "http://p1.meituan.net/biztone/16c41c82e79b66e01b5e3c2bb6e22225450990.jpg%40340w_255h_1e_1c_1l%7Cwatermark%3D0",
        "name_pinyin": "DOE coffee( tong ren lu dian )",
        "address": null,
        "address_pinyin": null,
        "rating": null,
        "review_count": null,
        "avg_price_per_person": null,
        "area": null,
        "category": null,
        "score_breakdown": null,
        "ranking_badge": null,
        "open_status": null,
        "opening_hours": null,
        "distance_from_station": null,
        "amenities": [],
        "recommended_dishes": [],
        "menu_count": null,
        "review_section_count": null
      },
      "offers": [],
      "extraction": {
        "status": "ok",
        "details_hidden": false,
        "captured_at": "2026-06-13T09:20:52.370Z",
        "method": "codex-extension",
        "elapsed_ms": 357
      }
    },
    {
      "scan_id": "2026-06-13T09:20:25.047Z",
      "source": {
        "base_url": "https://www.dianping.com/shanghai/ch10/r101937",
        "page_url": "https://www.dianping.com/shanghai/ch10/r101937d500p3",
        "page_number": 3,
        "result_index": 13
      },
      "shop": {
        "name": "西贡妈妈SaigonMama•越南料理(静安久光店)",
        "url": "https://www.dianping.com/shop/l6yO8n0kar5dJEUH",
        "shop_id": "l6yO8n0kar5dJEUH",
        "image_url": "https://img.meituan.net/content/1f717737962b285b8f2bca71abf5179f235090.jpg%40340w_255h_1e_1c_1l%7Cwatermark%3D0",
        "name_pinyin": "xi gong ma ma SaigonMama• yue nan liao li ( jing an jiu guang dian )",
        "address": null,
        "address_pinyin": null,
        "rating": null,
        "review_count": null,
        "avg_price_per_person": null,
        "area": null,
        "category": null,
        "score_breakdown": null,
        "ranking_badge": null,
        "open_status": null,
        "opening_hours": null,
        "distance_from_station": null,
        "amenities": [],
        "recommended_dishes": [],
        "menu_count": null,
        "review_section_count": null
      },
      "offers": [],
      "extraction": {
        "status": "ok",
        "details_hidden": false,
        "captured_at": "2026-06-13T09:20:52.755Z",
        "method": "codex-extension",
        "elapsed_ms": 381
      }
    },
    {
      "scan_id": "2026-06-13T09:20:25.047Z",
      "source": {
        "base_url": "https://www.dianping.com/shanghai/ch10/r101937",
        "page_url": "https://www.dianping.com/shanghai/ch10/r101937d500p3",
        "page_number": 3,
        "result_index": 14
      },
      "shop": {
        "name": "斐霓丝PHENIX(璞麗酒店)",
        "url": "https://www.dianping.com/shop/k1D1S8s2MTVobHUJ",
        "shop_id": "k1D1S8s2MTVobHUJ",
        "image_url": "https://img.meituan.net/content/57986e86d215e658cbc90124f2ef3f02126621.jpg%40340w_255h_1e_1c_1l%7Cwatermark%3D0",
        "name_pinyin": "fei ni si PHENIX( pu li jiu dian )",
        "address": null,
        "address_pinyin": null,
        "rating": null,
        "review_count": null,
        "avg_price_per_person": null,
        "area": null,
        "category": null,
        "score_breakdown": null,
        "ranking_badge": null,
        "open_status": null,
        "opening_hours": null,
        "distance_from_station": null,
        "amenities": [],
        "recommended_dishes": [],
        "menu_count": null,
        "review_section_count": null
      },
      "offers": [],
      "extraction": {
        "status": "ok",
        "details_hidden": false,
        "captured_at": "2026-06-13T09:20:53.110Z",
        "method": "codex-extension",
        "elapsed_ms": 349
      }
    },
    {
      "scan_id": "2026-06-13T09:20:25.047Z",
      "source": {
        "base_url": "https://www.dianping.com/shanghai/ch10/r101937",
        "page_url": "https://www.dianping.com/shanghai/ch10/r101937d500p3",
        "page_number": 3,
        "result_index": 15
      },
      "shop": {
        "name": "夜静安·摩登时代家宴",
        "url": "https://www.dianping.com/shop/l2DoYfeS0CTAE8Dm",
        "shop_id": "l2DoYfeS0CTAE8Dm",
        "image_url": "http://p0.meituan.net/biztone/bdc75b9337316ea414b4f57ce99fbb4d252584.jpg%40340w_255h_1e_1c_1l%7Cwatermark%3D0",
        "name_pinyin": "ye jing an · mo deng shi dai jia yan",
        "address": null,
        "address_pinyin": null,
        "rating": null,
        "review_count": null,
        "avg_price_per_person": null,
        "area": null,
        "category": null,
        "score_breakdown": null,
        "ranking_badge": null,
        "open_status": null,
        "opening_hours": null,
        "distance_from_station": null,
        "amenities": [],
        "recommended_dishes": [],
        "menu_count": null,
        "review_section_count": null
      },
      "offers": [],
      "extraction": {
        "status": "ok",
        "details_hidden": false,
        "captured_at": "2026-06-13T09:20:53.475Z",
        "method": "codex-extension",
        "elapsed_ms": 360
      }
    }
  ]
}
